nbcli/__init__.py
nbcli/__main__.py
nbcli/__version__.py
nbcli/cli.py
nbcli/commands/__init__.py
nbcli/commands/base.py
nbcli/commands/create.py
nbcli/commands/filter.py
nbcli/commands/info.py
nbcli/commands/init.py
nbcli/commands/search.py
nbcli/commands/shell.py
nbcli/commands/tools.py
nbcli/core/__init__.py
nbcli/core/config.py
nbcli/core/extend.py
nbcli/core/resolve_reference.yml
nbcli/core/utils.py
nbcli/user_defaults/__init__.py
nbcli/user_defaults/user_commands.py.default
nbcli/user_defaults/user_config.yml.default
nbcli/user_defaults/user_views.py.default
nbcli/views/__init__.py
nbcli/views/circuits.py
nbcli/views/dcim.py
nbcli/views/extras.py
nbcli/views/ipam.py
nbcli/views/tenancy.py
nbcli/views/tools.py
nbcli-0.10.0.dev2.dist-info/LICENSE
nbcli-0.10.0.dev2.dist-info/METADATA
nbcli-0.10.0.dev2.dist-info/WHEEL
nbcli-0.10.0.dev2.dist-info/entry_points.txt
nbcli-0.10.0.dev2.dist-info/top_level.txt
nbcli-0.10.0.dev2.dist-info/RECORD
