Metadata-Version: 2.1
Name: nbcli
Version: 0.10.0.dev2
Summary: CLI for netbox using pynetbox module
Author-email: Eric Geldmacher <egeldmacher@wustl.edu>
License: GPLv3
Project-URL: Documentation, https://nbcli.codeberg.page
Project-URL: Repository, https://codeberg.org/nbcli/nbcli
Project-URL: Bug Tracker, https://codeberg.org/nbcli/nbcli/issues
Classifier: Programming Language :: Python :: 3
Classifier: License :: OSI Approved :: GNU General Public License v3 (GPLv3)
Classifier: Operating System :: OS Independent
Requires-Python: >=3.8
License-File: LICENSE
Requires-Dist: pyyaml
Requires-Dist: pynetbox <8,>=7.3.4
Requires-Dist: setuptools
